sensirion_i2c_driver/__init__.py
sensirion_i2c_driver/command.py
sensirion_i2c_driver/connection.py
sensirion_i2c_driver/crc_calculator.py
sensirion_i2c_driver/device.py
sensirion_i2c_driver/errors.py
sensirion_i2c_driver/linux_i2c_transceiver.py
sensirion_i2c_driver/sensirion_command.py
sensirion_i2c_driver/transceiver_v1.py
sensirion_i2c_driver/version.py
sensirion_i2c_driver-1.0.0.dist-info/LICENSE
sensirion_i2c_driver-1.0.0.dist-info/METADATA
sensirion_i2c_driver-1.0.0.dist-info/WHEEL
sensirion_i2c_driver-1.0.0.dist-info/top_level.txt
sensirion_i2c_driver-1.0.0.dist-info/RECORD
