Metadata-Version: 2.1
Name: sensirion-i2c-driver
Version: 1.0.0
Summary: Base Driver for Communicating With I2C Devices
Home-page: https://github.com/sensirion/python-i2c-driver
Author: Urban Bruhin
Author-email: urban.bruhin@sensirion.com
License: BSD
Keywords: sensirion i2c driver
Platform: UNKNOWN
Classifier: Intended Audience :: Developers
Classifier: License :: OSI Approved :: BSD License
Classifier: Programming Language :: Python :: 2.7
Classifier: Programming Language :: Python :: 3.5
Classifier: Programming Language :: Python :: 3.6
Classifier: Programming Language :: Python :: 3.7
Classifier: Topic :: System :: Hardware :: Hardware Drivers
Requires-Python: >=2.7, !=3.0.*, !=3.1.*, !=3.2.*, !=3.3.*, !=3.4.*, <4
Provides-Extra: test
Requires-Dist: flake8 (~=3.6.0) ; extra == 'test'
Requires-Dist: mock (~=3.0.0) ; extra == 'test'
Requires-Dist: pytest (~=3.10.0) ; extra == 'test'
Requires-Dist: pytest-cov (~=2.6.0) ; extra == 'test'
